README.md
setup.py
exquisitor/__init__.py
exquisitor/display.py
exquisitor/exq_killall
exquisitor/page.py
exquisitor/run_session
exquisitor/web_session.py
exquisitor/webkitgtk.py
exquisitor/wmx.py
exquisitor.egg-info/PKG-INFO
exquisitor.egg-info/SOURCES.txt
exquisitor.egg-info/dependency_links.txt
exquisitor.egg-info/requires.txt
exquisitor.egg-info/top_level.txt