Metadata-Version: 2.1
Name: exquisitor
Version: 0.0.3
Summary: Exquisitor -- EXternal QUestion Internet SITe Online Researcher
Home-page: https://github.com/dbeal/exquisitor
Author: David J. Beal
Author-email: david.beal@protonmail.ch
License: UNKNOWN
Platform: UNKNOWN
Classifier: Programming Language :: Python :: 3
Classifier: License :: OSI Approved :: MIT License
Classifier: Operating System :: OS Independent
Requires-Python: >=2.7
